stix_shifter_modules/guardium/__init__.py
stix_shifter_modules/guardium/entry_point.py
stix_shifter_modules/guardium/configuration/config.json
stix_shifter_modules/guardium/configuration/dialects.json
stix_shifter_modules/guardium/configuration/lang_en.json
stix_shifter_modules/guardium/stix_translation/__init__.py
stix_shifter_modules/guardium/stix_translation/json_to_stix_translator.py
stix_shifter_modules/guardium/stix_translation/query_constructor.py
stix_shifter_modules/guardium/stix_translation/query_translator.py
stix_shifter_modules/guardium/stix_translation/transformers.py
stix_shifter_modules/guardium/stix_translation/json/guardium_qsearch_def.json
stix_shifter_modules/guardium/stix_translation/json/guardium_qsearch_params_map.json
stix_shifter_modules/guardium/stix_translation/json/guardium_report_params.json
stix_shifter_modules/guardium/stix_translation/json/guardium_report_params_map.json
stix_shifter_modules/guardium/stix_translation/json/guardium_reports_def.json
stix_shifter_modules/guardium/stix_translation/json/operators.json
stix_shifter_modules/guardium/stix_translation/json/qsearch_from_stix_map.json
stix_shifter_modules/guardium/stix_translation/json/reference_data_types4Query.json
stix_shifter_modules/guardium/stix_translation/json/report_from_stix_map.json
stix_shifter_modules/guardium/stix_translation/json/to_stix_map.json
stix_shifter_modules/guardium/stix_translation/json/stix_2_1/qsearch_from_stix_map.json
stix_shifter_modules/guardium/stix_translation/json/stix_2_1/report_from_stix_map.json
stix_shifter_modules/guardium/stix_translation/json/stix_2_1/to_stix_map.json
stix_shifter_modules/guardium/stix_transmission/__init__.py
stix_shifter_modules/guardium/stix_transmission/api_client.py
stix_shifter_modules/guardium/stix_transmission/delete_connector.py
stix_shifter_modules/guardium/stix_transmission/error_mapper.py
stix_shifter_modules/guardium/stix_transmission/guard_utils.py
stix_shifter_modules_guardium-8.0.2.dist-info/licenses/AUTHORS.md
stix_shifter_modules_guardium-8.0.2.dist-info/licenses/LICENSE.md
stix_shifter_modules_guardium-8.0.2.dist-info/licenses/NOTICE
stix_shifter_modules_guardium-8.0.2.dist-info/METADATA
stix_shifter_modules_guardium-8.0.2.dist-info/WHEEL
stix_shifter_modules_guardium-8.0.2.dist-info/top_level.txt
stix_shifter_modules_guardium-8.0.2.dist-info/RECORD
